llmforge/__init__.py
llmforge/exceptions.py
llmforge/py.typed
llmforge/utils.py
llmforge/agents/__init__.py
llmforge/agents/agent.py
llmforge/agents/models.py
llmforge/clients/__init__.py
llmforge/clients/gemini_client.py
llmforge/clients/opanai_client.py
llmforge/clients/parsers.py
llmforge/clients/utils.py
llmforge/llmwraper/__init__.py
llmforge/llmwraper/base_client.py
llmforge/llmwraper/langchain_hook_runner.py
llmforge/llmwraper/llm_hook_runner.py
llmforge/llmwraper/models.py
llmforge/llmwraper/hooks/__init__.py
llmforge/llmwraper/hooks/audit_hook.py
llmforge/llmwraper/hooks/base.py
llmforge/llmwraper/hooks/error_retry_hook.py
llmforge/llmwraper/hooks/input_length_hook.py
llmforge/llmwraper/hooks/rag_hook.py
llmforge/llmwraper/hooks/structured_output_hook.py
llmforge/llmwraper/hooks/tracing_hook.py
llmforge/models/__init__.py
llmforge/models/base.py
llmforge/models/fields.py
llmforge/parsers/__init__.py
llmforge/parsers/base.py
llmforge/parsers/utils.py
llmforge/prompt_builder/__init__.py
llmforge/prompt_builder/base_prompt.py
llmforge/prompt_builder/basic_prompt_components.py
llmforge/prompt_builder/builder.py
llmforge/prompt_hub/__init__.py
llmforge/prompt_hub/cli.py
llmforge/prompt_hub/models.py
llmforge/prompt_hub/prompt_hub.py
llmforge-0.0.2.dist-info/licenses/LICENSE
llmforge-0.0.2.dist-info/METADATA
llmforge-0.0.2.dist-info/WHEEL
llmforge-0.0.2.dist-info/entry_points.txt
llmforge-0.0.2.dist-info/top_level.txt
llmforge-0.0.2.dist-info/RECORD
