Metadata-Version: 2.4
Name: llmforge
Version: 0.0.2
Summary: Placeholder package to reserve the llmforge name
Author-email: Anik Mallick <anik.mallick.code@gmail.com>
License: MIT
Keywords: llm,generative-ai,rag,prompt-engineering
Classifier: Development Status :: 1 - Planning
Classifier: Programming Language :: Python :: 3
Classifier: License :: OSI Approved :: MIT License
Classifier: Operating System :: OS Independent
Requires-Python: >=3.8
License-File: LICENSE
Requires-Dist: pydantic==2.11.3
Requires-Dist: pyyaml
Requires-Dist: types-PyYAML
Requires-Dist: openai
Requires-Dist: tiktoken
Provides-Extra: dev
Requires-Dist: pytest; extra == "dev"
Requires-Dist: mypy; extra == "dev"
Provides-Extra: gemini
Requires-Dist: google-genai; extra == "gemini"
Dynamic: license-file
